LICENSE
README.md
setup.py
nist80022/ApproximateEntropy.py
nist80022/BinaryMatrix.py
nist80022/Complexity.py
nist80022/CumulativeSum.py
nist80022/FrequencyTest.py
nist80022/Matrix.py
nist80022/RandomExcursions.py
nist80022/RunTest.py
nist80022/Serial.py
nist80022/Spectral.py
nist80022/TemplateMatching.py
nist80022/Tools.py
nist80022/Universal.py
nist80022/__init__.py
nist80022.egg-info/PKG-INFO
nist80022.egg-info/SOURCES.txt
nist80022.egg-info/dependency_links.txt
nist80022.egg-info/requires.txt
nist80022.egg-info/top_level.txt