Metadata-Version: 2.1
Name: nist80022
Version: 0.2.0
Summary: Library for implementing NIST 800-22 testsuite.
Home-page: https://github.com/cpagravel/randomness_testsuite
Maintainer: Chris Gravel
Maintainer-email: cpagravel@gmail.com
License: MIT
Download-URL: https://github.com/cpagravel/randomness_testsuite/archive/0.1.0.tar.gz
Keywords: Randomness,NIST Test Suite,SP80022,NIST 800-22
Platform: UNKNOWN
Classifier: Development Status :: 4 - Beta
Classifier: Intended Audience :: Science/Research
Classifier: Topic :: Security :: Cryptography
Classifier: License :: OSI Approved :: MIT License
Classifier: Programming Language :: Python :: 3
Classifier: Programming Language :: Python :: 3.6
Classifier: Programming Language :: Python :: 3.7
Classifier: Programming Language :: Python :: 3.8
Classifier: Programming Language :: Python :: 3.9
License-File: LICENSE
